p3dit/__init__.py
p3dit/cli.py
p3dit/editor.py
p3dit/fifteen.ttf
p3dit/highlight.py
p3dit/text.py
p3dit-0.1.dist-info/LICENSE.txt
p3dit-0.1.dist-info/METADATA
p3dit-0.1.dist-info/WHEEL
p3dit-0.1.dist-info/entry_points.txt
p3dit-0.1.dist-info/top_level.txt
p3dit-0.1.dist-info/RECORD
