Metadata-Version: 2.1
Name: p3dit
Version: 0.1
Summary: Simple text editor in Panda3D
Home-page: https://codeberg.org/entikan/p3dit
Author: jan Entikan
License: MIT
Keywords: panda3d gamedev
Platform: UNKNOWN
Classifier: Development Status :: 4 - Beta
Classifier: License :: OSI Approved :: MIT License
Classifier: Programming Language :: Python
Classifier: Programming Language :: Python :: 3
Classifier: Programming Language :: Python :: 3.6
Classifier: Programming Language :: Python :: 3.7
Classifier: Programming Language :: Python :: 3.8
License-File: LICENSE.txt
Requires-Dist: panda3d
Requires-Dist: pygments
Requires-Dist: DirectFolderBrowser
